worldometer/__about__.py
worldometer/__init__.py
worldometer/api.py
worldometer/core.py
worldometer-1.0.1.dist-info/LICENSE
worldometer-1.0.1.dist-info/METADATA
worldometer-1.0.1.dist-info/WHEEL
worldometer-1.0.1.dist-info/top_level.txt
worldometer-1.0.1.dist-info/RECORD
