Metadata-Version: 2.1
Name: worldometer
Version: 1.0.1
Summary: Worldometer Scraping & API - Get world metrics from worldometers.info
Home-page: https://github.com/matheusfelipeog/worldometer
Author: Matheus Felipe
Author-email: matheusfelipeog@protonmail.com
License: MIT License
Project-URL: Bug Tracker, https://github.com/matheusfelipeog/worldometer/issues
Project-URL: Documentation, https://worldometer.readthedocs.io
Project-URL: Source Code, https://github.com/matheusfelipeog/worldometer
Keywords: worldometer,worldometers,worldometer-api,worldometer-scraping,world-data,world-metrics,metrics,real-time-data,real-time-metrics,api,scraping,requests-html
Platform: UNKNOWN
Classifier: Development Status :: 5 - Production/Stable
Classifier: Intended Audience :: Developers
Classifier: Intended Audience :: Information Technology
Classifier: License :: OSI Approved :: MIT License
Classifier: Natural Language :: English
Classifier: Operating System :: OS Independent
Classifier: Programming Language :: Python
Classifier: Programming Language :: Python :: 3.6
Classifier: Programming Language :: Python :: 3.7
Classifier: Programming Language :: Python :: 3.8
Classifier: Programming Language :: Python :: 3.9
Classifier: Programming Language :: Python :: Implementation :: CPython
Classifier: Topic :: Software Development :: Libraries
Classifier: Topic :: Software Development :: Libraries :: Python Modules
Requires-Python: >=3.6
